CHANGES.txt
LICENSE.txt
MANIFEST.in
setup.py
Unirest.egg-info/PKG-INFO
Unirest.egg-info/SOURCES.txt
Unirest.egg-info/dependency_links.txt
Unirest.egg-info/requires.txt
Unirest.egg-info/top_level.txt
unirest/__init__.py