Metadata-Version: 1.0
Name: Unirest
Version: 1.0.5
Summary: Unirest, the lightweight HTTP library
Home-page: http://pypi.python.org/pypi/Unirest/
Author: Mashape Inc.
Author-email: support@mashape.com
License: LICENSE.txt
Platform: UNKNOWN
